cowboe.py
cowboe-1.0.9.data/data/LICENSE.txt
cowboe-1.0.9.dist-info/LICENSE.txt
cowboe-1.0.9.dist-info/METADATA
cowboe-1.0.9.dist-info/WHEEL
cowboe-1.0.9.dist-info/top_level.txt
cowboe-1.0.9.dist-info/RECORD
